dsnparse.py
dsnparse-0.4.0.dist-info/licenses/LICENSE.txt
dsnparse-0.4.0.dist-info/METADATA
dsnparse-0.4.0.dist-info/WHEEL
dsnparse-0.4.0.dist-info/top_level.txt
dsnparse-0.4.0.dist-info/RECORD
