Metadata-Version: 2.4
Name: dsnparse
Version: 0.4.0
Summary: parse dsn urls
Author-email: Jay Marcyes <jay@marcyes.com>
License-Expression: MIT
Project-URL: Repository, https://github.com/Jaymon/dsnparse
Project-URL: Homepage, http://github.com/Jaymon/dsnparse
Keywords: dsn url parser database configuration
Classifier: Development Status :: 5 - Production/Stable
Classifier: Environment :: Plugins
Classifier: Intended Audience :: Developers
Classifier: Operating System :: OS Independent
Classifier: Programming Language :: Python :: 3
Requires-Python: >=3.10
License-File: LICENSE.txt
Dynamic: license-file
